dephell_setuptools-0.2.5.dist-info/dependency_links.txt
dephell_setuptools-0.2.5.dist-info/entry_points.txt
dephell_setuptools-0.2.5.dist-info/METADATA
dephell_setuptools-0.2.5.dist-info/top_level.txt
dephell_setuptools-0.2.5.dist-info/WHEEL
dephell_setuptools/distutils_cmd.py
dephell_setuptools/_cmd.py
dephell_setuptools/_cli.py
dephell_setuptools/_pkginfo.py
dephell_setuptools/_manager.py
dephell_setuptools/_base.py
dephell_setuptools/_cached_property.py
dephell_setuptools/__main__.py
dephell_setuptools/_cfg.py
dephell_setuptools/_constants.py
dephell_setuptools/_static.py
dephell_setuptools/__init__.py
dephell_setuptools-0.2.5.dist-info/LICENSE
dephell_setuptools-0.2.5.dist-info/RECORD